{"skeleton":{"hash":"/L0JETge3Uw","spine":"4.2.43","x":-3539.9,"y":-1456.29,"width":5465.19,"height":3827.71,"images":"./SC/Spine_SC/","audio":"./audio"},"bones":[{"name":"crashgame_bg_loop"},{"name":"Asteroid","parent":"crashgame_bg_loop","x":848.59,"y":-524.45,"scaleX":1.2,"scaleY":1.2,"color":"02ff10ff"},{"name":"Asteroid_01","parent":"Asteroid","rotation":35.1,"x":129.83,"y":115.27,"scaleX":2,"scaleY":2,"color":"00fc22ff","icon":"star"},{"name":"Asteroid_02","parent":"Asteroid","x":35.63,"y":3.91,"scaleX":2.5,"scaleY":2.5,"color":"00fc22ff","icon":"star"},{"name":"Asteroid_03","parent":"Asteroid","x":121.5,"y":-5.42,"scaleX":2,"scaleY":2,"color":"00fc22ff","icon":"star"},{"name":"Asteroid_04","parent":"Asteroid","x":-134.6,"y":-78.51,"scaleX":3,"scaleY":3,"color":"00fc22ff","icon":"star"},{"name":"Asteroid_05","parent":"Asteroid","x":-79.37,"y":20.61,"scaleX":3,"scaleY":3,"color":"00fc22ff","icon":"star"},{"name":"Metoer","parent":"crashgame_bg_loop","x":1119.75,"color":"03ffd6ff"},{"name":"Planet","parent":"crashgame_bg_loop","x":-594.21,"y":1145.36,"color":"ff0101ff"},{"name":"Planet_01","parent":"crashgame_bg_loop","length":250,"x":-658.54,"y":1079.62,"scaleX":1.5,"scaleY":1.5,"color":"ff0000ff"},{"name":"Planet_08","parent":"Planet","length":80,"x":249.23,"y":-2379.72,"scaleX":2.5,"scaleY":2.5,"color":"ff0000ff"},{"name":"Planet_07","parent":"Planet","length":50,"x":683.72,"y":-1907.95,"color":"ff0000ff"},{"name":"Planet_05","parent":"Planet","length":150,"x":1022.73,"y":-82.97,"scaleX":1.5,"scaleY":1.5,"color":"ff0000ff"},{"name":"Planet_04","parent":"Planet","length":100,"x":765.13,"y":-1762.33,"scaleX":2,"scaleY":2,"color":"ff0000ff"},{"name":"Planet_03","parent":"Planet","length":150,"x":-136.7,"y":-1422.28,"scaleX":2,"scaleY":2,"color":"ff0000ff"},{"name":"Planet_02","parent":"Planet","length":100,"x":350.23,"y":-855.57,"color":"ff0000ff"},{"name":"Planet_02_line","parent":"Planet_02","y":-0.5},{"name":"meteor_08","parent":"Metoer","rotation":-2.25,"x":266.2,"y":-450.89,"scaleX":2,"scaleY":2,"color":"00ffc8ff","icon":"ik"},{"name":"meteor_07","parent":"Metoer","x":287.15,"y":-108.71,"scaleX":2,"scaleY":2,"color":"00ffc8ff","icon":"ik"},{"name":"meteor_06","parent":"Metoer","x":561.83,"y":59.21,"scaleX":2,"scaleY":2,"color":"00ffd2ff","icon":"circle"},{"name":"meteor_05","parent":"Metoer","x":639.9,"y":588.06,"scaleX":1.5,"scaleY":1.5,"color":"00ffd2ff","icon":"circle"},{"name":"meteor_04","parent":"Metoer","rotation":-72,"x":136.04,"y":-201.04,"scaleX":2,"scaleY":2,"color":"00ffd2ff","icon":"circle"},{"name":"meteor_03","parent":"Metoer","x":346.8,"y":41.1,"scaleX":2,"scaleY":2,"color":"00ffd2ff","icon":"circle"},{"name":"meteor_02","parent":"Metoer","rotation":-12.83,"x":629.5,"y":212.12,"scaleX":2,"scaleY":2,"color":"00ffd2ff","icon":"circle"},{"name":"meteor_01","parent":"Metoer","x":346.68,"y":178.62,"scaleX":1.5,"scaleY":1.5,"color":"00ffd2ff","icon":"circle"},{"name":"Planet_09","parent":"Planet","length":150,"x":1321.25,"y":-2154.08,"scaleX":1.4,"scaleY":1.4,"color":"ff0000ff"},{"name":"Planet_09_line","parent":"Planet_09","x":0.36,"scaleX":1.2,"scaleY":1.2},{"name":"Planet_02_line_glow","parent":"Planet_02","length":100,"x":-2.05,"y":-3.65,"color":"ff0707ff"},{"name":"Planet_09_line_glow","parent":"Planet_09_line","x":-5.03,"y":10.56},{"name":"Planet3","parent":"crashgame_bg_loop","rotation":-120,"x":-594.21,"y":1145.36,"color":"ff0101ff"},{"name":"Planet_019","parent":"Planet3","length":80,"x":249.23,"y":-2379.72,"scaleX":2.5,"scaleY":2.5,"color":"ff0000ff"},{"name":"Planet_020","parent":"Planet3","length":50,"x":683.72,"y":-1907.95,"color":"ff0000ff"},{"name":"Planet_021","parent":"Planet3","length":50,"x":1039.57,"y":-372.16,"scaleX":1.5,"scaleY":1.5,"color":"ff0000ff"},{"name":"Planet_022","parent":"Planet3","length":150,"x":1022.73,"y":-82.97,"scaleX":1.5,"scaleY":1.5,"color":"ff0000ff"},{"name":"Planet_023","parent":"Planet3","length":100,"x":765.13,"y":-1762.33,"scaleX":2,"scaleY":2,"color":"ff0000ff"},{"name":"Planet_024","parent":"Planet3","length":150,"x":-136.7,"y":-1422.28,"scaleX":2,"scaleY":2,"color":"ff0000ff"},{"name":"Planet_025","parent":"Planet3","length":100,"x":350.23,"y":-855.57,"color":"ff0000ff"},{"name":"Planet_02_line3","parent":"Planet_025","y":-0.5},{"name":"Planet_02_line_glow3","parent":"Planet_025","length":100,"x":-2.05,"y":-3.65,"color":"ff0707ff"},{"name":"Planet_026","parent":"Planet3","length":150,"x":1321.25,"y":-2154.08,"scaleX":1.4,"scaleY":1.4,"color":"ff0000ff"},{"name":"Planet_09_line3","parent":"Planet_026","x":0.36,"scaleX":1.2,"scaleY":1.2},{"name":"Planet_09_line_glow3","parent":"Planet_09_line3","x":-5.03,"y":10.56},{"name":"Planet_027","parent":"Planet","length":50,"rotation":-120,"x":1041.05,"y":-371.82,"scaleX":1.5,"scaleY":1.5,"color":"ff0000ff"},{"name":"front","parent":"crashgame_bg_loop","x":-643.54,"y":1103.62,"color":"00ff18ff","icon":"diamond"},{"name":"back","parent":"crashgame_bg_loop","x":-643.54,"y":1103.62,"color":"ff00a7ff","icon":"diamond"},{"name":"Metoer2","parent":"crashgame_bg_loop","x":1119.75,"color":"03ffd6ff"},{"name":"meteor_09","parent":"Metoer2","rotation":-2.25,"x":266.2,"y":-450.89,"scaleX":2,"scaleY":2,"color":"00ffc8ff","icon":"ik"},{"name":"meteor_010","parent":"Metoer2","x":287.15,"y":-108.71,"scaleX":2,"scaleY":2,"color":"00ffc8ff","icon":"ik"},{"name":"meteor_011","parent":"Metoer2","x":561.83,"y":59.21,"scaleX":2,"scaleY":2,"color":"00ffd2ff","icon":"circle"},{"name":"meteor_012","parent":"Metoer2","x":639.9,"y":588.06,"scaleX":1.5,"scaleY":1.5,"color":"00ffd2ff","icon":"circle"},{"name":"meteor_013","parent":"Metoer2","rotation":-72,"x":136.04,"y":-201.04,"scaleX":2,"scaleY":2,"color":"00ffd2ff","icon":"circle"},{"name":"meteor_014","parent":"Metoer2","x":346.8,"y":41.1,"scaleX":2,"scaleY":2,"color":"00ffd2ff","icon":"circle"},{"name":"meteor_015","parent":"Metoer2","rotation":-12.83,"x":629.5,"y":212.12,"scaleX":2,"scaleY":2,"color":"00ffd2ff","icon":"circle"},{"name":"meteor_016","parent":"Metoer2","x":346.68,"y":178.62,"scaleX":1.5,"scaleY":1.5,"color":"00ffd2ff","icon":"circle"},{"name":"Metoer3","parent":"crashgame_bg_loop","x":1119.75,"color":"03ffd6ff"},{"name":"meteor_017","parent":"Metoer3","rotation":-2.25,"x":266.2,"y":-450.89,"scaleX":2,"scaleY":2,"color":"00ffc8ff","icon":"ik"},{"name":"meteor_018","parent":"Metoer3","x":287.15,"y":-108.71,"scaleX":2,"scaleY":2,"color":"00ffc8ff","icon":"ik"},{"name":"meteor_019","parent":"Metoer3","x":561.83,"y":59.21,"scaleX":2,"scaleY":2,"color":"00ffd2ff","icon":"circle"},{"name":"meteor_020","parent":"Metoer3","x":639.9,"y":588.06,"scaleX":1.5,"scaleY":1.5,"color":"00ffd2ff","icon":"circle"},{"name":"meteor_021","parent":"Metoer3","rotation":-72,"x":136.04,"y":-201.04,"scaleX":2,"scaleY":2,"color":"00ffd2ff","icon":"circle"},{"name":"meteor_022","parent":"Metoer3","x":346.8,"y":41.1,"scaleX":2,"scaleY":2,"color":"00ffd2ff","icon":"circle"},{"name":"meteor_023","parent":"Metoer3","rotation":-12.83,"x":629.5,"y":212.12,"scaleX":2,"scaleY":2,"color":"00ffd2ff","icon":"circle"},{"name":"meteor_024","parent":"Metoer3","x":346.68,"y":178.62,"scaleX":1.5,"scaleY":1.5,"color":"00ffd2ff","icon":"circle"},{"name":"Asteroid2","parent":"crashgame_bg_loop","x":848.59,"y":-524.45,"scaleX":1.2,"scaleY":1.2,"color":"02ff10ff"},{"name":"Asteroid_06","parent":"Asteroid2","rotation":35.1,"x":129.83,"y":115.27,"scaleX":2,"scaleY":2,"color":"00fc22ff","icon":"star"},{"name":"Asteroid_07","parent":"Asteroid2","x":35.63,"y":3.91,"scaleX":2.5,"scaleY":2.5,"color":"00fc22ff","icon":"star"},{"name":"Asteroid_08","parent":"Asteroid2","x":121.5,"y":-5.42,"scaleX":2,"scaleY":2,"color":"00fc22ff","icon":"star"},{"name":"Asteroid_09","parent":"Asteroid2","x":-134.6,"y":-78.51,"scaleX":3,"scaleY":3,"color":"00fc22ff","icon":"star"},{"name":"Asteroid_010","parent":"Asteroid2","x":-79.37,"y":20.61,"scaleX":3,"scaleY":3,"color":"00fc22ff","icon":"star"},{"name":"Asteroid3","parent":"crashgame_bg_loop","x":848.59,"y":-524.45,"scaleX":1.2,"scaleY":1.2,"color":"02ff10ff"},{"name":"Asteroid_011","parent":"Asteroid3","rotation":35.1,"x":129.83,"y":115.27,"scaleX":2,"scaleY":2,"color":"00fc22ff","icon":"star"},{"name":"Asteroid_012","parent":"Asteroid3","x":35.63,"y":3.91,"scaleX":2.5,"scaleY":2.5,"color":"00fc22ff","icon":"star"},{"name":"Asteroid_013","parent":"Asteroid3","x":121.5,"y":-5.42,"scaleX":2,"scaleY":2,"color":"00fc22ff","icon":"star"},{"name":"Asteroid_014","parent":"Asteroid3","x":-134.6,"y":-78.51,"scaleX":3,"scaleY":3,"color":"00fc22ff","icon":"star"},{"name":"Asteroid_015","parent":"Asteroid3","x":-79.37,"y":20.61,"scaleX":3,"scaleY":3,"color":"00fc22ff","icon":"star"},{"name":"bg_light","parent":"crashgame_bg_loop","x":108,"scaleX":2,"scaleY":1.5}],"slots":[{"name":"Planet_01","bone":"Planet_01","attachment":"Planet_01"},{"name":"Planet_02","bone":"Planet_02","attachment":"Planet_02"},{"name":"Planet_025","bone":"Planet_025","attachment":"Planet_02"},{"name":"Planet_02_line","bone":"Planet_02_line","attachment":"Planet_02_line"},{"name":"Planet_02_line3","bone":"Planet_02_line3","attachment":"Planet_02_line"},{"name":"Planet_03","bone":"Planet_03","attachment":"Planet_03"},{"name":"Planet_024","bone":"Planet_024","attachment":"Planet_03"},{"name":"Planet_04","bone":"Planet_04","attachment":"Planet_04"},{"name":"Planet_023","bone":"Planet_023","attachment":"Planet_04"},{"name":"Planet_05","bone":"Planet_05","attachment":"Planet_05"},{"name":"Planet_022","bone":"Planet_022","attachment":"Planet_05"},{"name":"Planet_021","bone":"Planet_021","attachment":"Planet_06"},{"name":"Planet_027","bone":"Planet_027","attachment":"Planet_06"},{"name":"Planet_07","bone":"Planet_07","attachment":"Planet_07"},{"name":"Planet_020","bone":"Planet_020","attachment":"Planet_07"},{"name":"Planet_08","bone":"Planet_08","attachment":"Planet_08"},{"name":"Planet_019","bone":"Planet_019","attachment":"Planet_08"},{"name":"Planet_09","bone":"Planet_09","attachment":"Planet_09"},{"name":"Planet_026","bone":"Planet_026","attachment":"Planet_09"},{"name":"Planet_09_line","bone":"Planet_09_line","attachment":"Planet_09_line"},{"name":"Planet_09_line3","bone":"Planet_09_line3","attachment":"Planet_09_line"},{"name":"Planet_02_line_glow","bone":"Planet_02_line_glow","color":"ffffff22","attachment":"Planet_02_line_glow","blend":"additive"},{"name":"Planet_02_line_glow3","bone":"Planet_02_line_glow3","color":"ffffff22","attachment":"Planet_02_line_glow","blend":"additive"},{"name":"Planet_09_line_glow","bone":"Planet_09_line_glow","color":"ffffff62","blend":"additive"},{"name":"Planet_09_line_glow3","bone":"Planet_09_line_glow3","color":"ffffff62","blend":"additive"},{"name":"Asteroid_01","bone":"Asteroid_01","attachment":"Asteroid_01"},{"name":"Asteroid_06","bone":"Asteroid_06","attachment":"Asteroid_01"},{"name":"Asteroid_011","bone":"Asteroid_011","attachment":"Asteroid_01"},{"name":"Asteroid_02","bone":"Asteroid_02","attachment":"Asteroid_02"},{"name":"Asteroid_07","bone":"Asteroid_07","attachment":"Asteroid_02"},{"name":"Asteroid_012","bone":"Asteroid_012","attachment":"Asteroid_02"},{"name":"Asteroid_03","bone":"Asteroid_03","attachment":"Asteroid_03"},{"name":"Asteroid_08","bone":"Asteroid_08","attachment":"Asteroid_03"},{"name":"Asteroid_013","bone":"Asteroid_013","attachment":"Asteroid_03"},{"name":"Asteroid_04","bone":"Asteroid_04","attachment":"Asteroid_04"},{"name":"Asteroid_09","bone":"Asteroid_09","attachment":"Asteroid_04"},{"name":"Asteroid_014","bone":"Asteroid_014","attachment":"Asteroid_04"},{"name":"Asteroid_05","bone":"Asteroid_05","attachment":"Asteroid_05"},{"name":"Asteroid_010","bone":"Asteroid_010","attachment":"Asteroid_05"},{"name":"Asteroid_015","bone":"Asteroid_015","attachment":"Asteroid_05"},{"name":"meteor_01","bone":"meteor_01","attachment":"meteor_01"},{"name":"meteor_016","bone":"meteor_016","attachment":"meteor_01"},{"name":"meteor_024","bone":"meteor_024","attachment":"meteor_01"},{"name":"meteor_02","bone":"meteor_02","attachment":"meteor_02"},{"name":"meteor_015","bone":"meteor_015","attachment":"meteor_02"},{"name":"meteor_023","bone":"meteor_023","attachment":"meteor_02"},{"name":"meteor_03","bone":"meteor_03","attachment":"meteor_03"},{"name":"meteor_014","bone":"meteor_014","attachment":"meteor_03"},{"name":"meteor_022","bone":"meteor_022","attachment":"meteor_03"},{"name":"meteor_04","bone":"meteor_04","attachment":"meteor_04"},{"name":"meteor_013","bone":"meteor_013","attachment":"meteor_04"},{"name":"meteor_021","bone":"meteor_021","attachment":"meteor_04"},{"name":"meteor_05","bone":"meteor_05","attachment":"meteor_05"},{"name":"meteor_012","bone":"meteor_012","attachment":"meteor_05"},{"name":"meteor_020","bone":"meteor_020","attachment":"meteor_05"},{"name":"meteor_06","bone":"meteor_06","attachment":"meteor_06"},{"name":"meteor_011","bone":"meteor_011","attachment":"meteor_06"},{"name":"meteor_019","bone":"meteor_019","attachment":"meteor_06"},{"name":"meteor_07","bone":"meteor_07","attachment":"meteor_07"},{"name":"meteor_010","bone":"meteor_010","attachment":"meteor_07"},{"name":"meteor_018","bone":"meteor_018","attachment":"meteor_07"},{"name":"meteor_08","bone":"meteor_08","attachment":"meteor_08"},{"name":"meteor_09","bone":"meteor_09","attachment":"meteor_08"},{"name":"meteor_017","bone":"meteor_017","attachment":"meteor_08"},{"name":"bg_light","bone":"bg_light","attachment":"bg_light"}],"transform":[{"name":"cont","bones":["back"],"target":"front","mixRotate":-1,"mixX":-1,"mixScaleX":-1,"mixShearY":-1}],"skins":[{"name":"default","attachments":{"Asteroid_01":{"Asteroid_01":{"width":76,"height":45}},"Asteroid_02":{"Asteroid_02":{"width":17,"height":23}},"Asteroid_03":{"Asteroid_03":{"width":41,"height":27}},"Asteroid_04":{"Asteroid_04":{"width":32,"height":35}},"Asteroid_05":{"Asteroid_05":{"width":16,"height":29}},"Asteroid_06":{"Asteroid_01":{"width":76,"height":45}},"Asteroid_07":{"Asteroid_02":{"width":17,"height":23}},"Asteroid_08":{"Asteroid_03":{"width":41,"height":27}},"Asteroid_09":{"Asteroid_04":{"width":32,"height":35}},"Asteroid_010":{"Asteroid_05":{"width":16,"height":29}},"Asteroid_011":{"Asteroid_01":{"width":76,"height":45}},"Asteroid_012":{"Asteroid_02":{"width":17,"height":23}},"Asteroid_013":{"Asteroid_03":{"width":41,"height":27}},"Asteroid_014":{"Asteroid_04":{"width":32,"height":35}},"Asteroid_015":{"Asteroid_05":{"width":16,"height":29}},"bg_light":{"bg_light":{"width":1000,"height":1000}},"meteor_01":{"meteor_01":{"width":109,"height":126}},"meteor_02":{"meteor_02":{"width":158,"height":99}},"meteor_03":{"meteor_03":{"width":34,"height":35}},"meteor_04":{"meteor_04":{"width":138,"height":76}},"meteor_05":{"meteor_05":{"width":157,"height":197}},"meteor_06":{"meteor_06":{"width":74,"height":52}},"meteor_07":{"meteor_07":{"width":28,"height":32}},"meteor_08":{"meteor_08":{"x":-4.43,"y":-0.25,"rotation":17.77,"width":116,"height":66}},"meteor_09":{"meteor_08":{"x":-4.43,"y":-0.25,"rotation":17.77,"width":116,"height":66}},"meteor_010":{"meteor_07":{"width":28,"height":32}},"meteor_011":{"meteor_06":{"width":74,"height":52}},"meteor_012":{"meteor_05":{"width":157,"height":197}},"meteor_013":{"meteor_04":{"width":138,"height":76}},"meteor_014":{"meteor_03":{"width":34,"height":35}},"meteor_015":{"meteor_02":{"width":158,"height":99}},"meteor_016":{"meteor_01":{"width":109,"height":126}},"meteor_017":{"meteor_08":{"x":-4.43,"y":-0.25,"rotation":17.77,"width":116,"height":66}},"meteor_018":{"meteor_07":{"width":28,"height":32}},"meteor_019":{"meteor_06":{"width":74,"height":52}},"meteor_020":{"meteor_05":{"width":157,"height":197}},"meteor_021":{"meteor_04":{"width":138,"height":76}},"meteor_022":{"meteor_03":{"width":34,"height":35}},"meteor_023":{"meteor_02":{"width":158,"height":99}},"meteor_024":{"meteor_01":{"width":109,"height":126}},"Planet_01":{"Planet_01":{"type":"mesh","uvs":[0.90517,0.09415,0.99638,0.28552,0.99996,0.48759,0.9938,0.68702,0.9518,0.79743,0.85882,0.89822,0.6613,1,0.40734,1,0.21788,0.93369,0.09493,0.81939,0,0.63808,0,0.45188,0,0.27349,0.05808,0.17902,0.11509,0.08627,0.31664,0,0.71571,0,0.56171,0.21751,0.70681,0.67516,0.58152,0.76171,0.44501,0.76322,0.29591,0.7082,0.2224,0.36634,0.29054,0.28863,0.4191,0.21269,0.51215,0.49421,0.70032,0.28487,0.20148,0.50495,0.23449,0.62581,0.77898,0.41758,0.77786,0.5455],"triangles":[19,20,25,18,25,30,25,26,29,30,25,29,17,24,15,16,17,15,26,17,16,26,16,0,26,0,1,23,14,15,23,15,24,13,14,23,22,13,23,12,13,22,11,12,22,29,1,2,25,24,17,23,24,25,27,11,22,28,27,25,10,11,27,10,27,28,3,30,2,21,28,25,20,21,25,4,18,3,9,10,28,9,28,21,5,18,4,19,18,5,8,9,21,8,21,20,7,8,20,6,19,5,7,20,19,6,7,19,22,23,25,27,22,25,29,26,1,30,29,2,18,30,3,19,25,18,25,17,26],"vertices":[1,44,546.14,551.72,1,1,44,671.29,280.71,1,1,44,677.57,-5.99,1,1,44,671.29,-289.13,1,1,44,603.51,-443.74,1,1,44,481.88,-588.04,1,1,44,208.12,-732.32,1,1,44,-143.86,-732.32,1,1,44,-406.45,-638.32,1,1,44,-576.86,-476.3,1,2,44,-708.44,-219.3,0.95,43,-708.44,-219.3,0.05,1,44,-708.44,44.64,1,1,44,-708.44,297.5,1,1,44,-627.94,431.42,1,1,44,-548.92,562.89,1,1,44,-269.57,685.18,1,1,44,283.54,685.18,1,2,44,84.97,369.9,0.6,43,84.97,369.9,0.4,2,44,274.17,-273.24,0.6846,43,274.17,-273.24,0.3154,2,44,100.93,-396.12,0.7,43,100.93,-396.12,0.3,2,44,-89.1,-397.88,0.7769,43,-89.1,-397.88,0.2231,2,44,-292.72,-321.31,0.6538,43,-292.72,-321.31,0.3462,2,44,-394.66,163.11,0.7692,43,-394.66,163.11,0.2308,2,44,-300.3,273.5,0.7308,43,-300.3,273.5,0.2692,2,44,-121.17,380.69,0.6692,43,-121.17,380.69,0.3308,2,44,1.4,-15.37,0.5,43,1.4,-15.37,0.5,2,44,450.83,279,0.5692,43,-9.92,279.72,0.4308,2,44,-244.28,-31.16,0.6,43,-705.03,-30.44,0.4,2,44,-198.27,-202.6,0.6,43,-659.02,-201.88,0.4,2,44,392.41,83.34,0.6308,43,318.3,118.05,0.3692,2,44,392.41,-98.68,0.6615,43,318.3,-63.97,0.3385],"hull":17,"edges":[18,16,16,14,12,14,12,10,18,20,28,30,30,32,32,0,0,2,36,38,38,40,40,42,44,46,46,48,48,34,34,52,2,4,4,6,54,44,24,26,26,28,20,22,22,24,42,56,6,8,8,10,58,60,60,36,58,52,54,56],"width":616,"height":630}},"Planet_02":{"Planet_02":{"width":288,"height":289}},"Planet_02_line":{"Planet_02_line":{"width":464,"height":348}},"Planet_02_line3":{"Planet_02_line":{"width":464,"height":348}},"Planet_02_line_glow":{"Planet_02_line_glow":{"width":464,"height":348}},"Planet_02_line_glow3":{"Planet_02_line_glow":{"width":464,"height":348}},"Planet_03":{"Planet_03":{"x":4.46,"y":3.83,"width":263,"height":263}},"Planet_04":{"Planet_04":{"width":151,"height":151}},"Planet_05":{"Planet_05":{"width":249,"height":248}},"Planet_07":{"Planet_07":{"width":91,"height":91}},"Planet_08":{"Planet_08":{"scaleX":1.2,"scaleY":1.2,"rotation":-13.27,"width":123,"height":123}},"Planet_09":{"Planet_09":{"width":319,"height":319}},"Planet_09_line":{"Planet_09_line":{"width":290,"height":409}},"Planet_09_line3":{"Planet_09_line":{"width":290,"height":409}},"Planet_09_line_glow":{"Planet_09_line_glow":{"x":5.81,"y":-9.12,"width":290,"height":409}},"Planet_09_line_glow3":{"Planet_09_line_glow":{"x":5.81,"y":-9.12,"width":290,"height":409}},"Planet_019":{"Planet_08":{"scaleX":1.2,"scaleY":1.2,"width":123,"height":123}},"Planet_020":{"Planet_07":{"width":91,"height":91}},"Planet_021":{"Planet_06":{"x":-3.01,"y":6.82,"width":71,"height":71}},"Planet_022":{"Planet_05":{"width":249,"height":248}},"Planet_023":{"Planet_04":{"width":151,"height":151}},"Planet_024":{"Planet_03":{"x":4.46,"y":3.83,"width":263,"height":263}},"Planet_025":{"Planet_02":{"width":288,"height":289}},"Planet_026":{"Planet_09":{"width":319,"height":319}},"Planet_027":{"Planet_06":{"x":-3.01,"y":6.82,"width":71,"height":71}}}}],"animations":{"Crashgame_bg":{"slots":{"Planet_02_line_glow":{"rgba":[{"color":"ffffff23"},{"time":1.6667,"color":"ffffffc7"},{"time":3.3333,"color":"ffffff23"},{"time":5,"color":"ffffffc7"},{"time":6.6667,"color":"ffffff23"},{"time":8.3333,"color":"ffffffc7"},{"time":10,"color":"ffffff23"},{"time":11.7,"color":"ffffffc7"},{"time":13.3667,"color":"ffffff23"},{"time":15,"color":"ffffffc7"},{"time":16.6667,"color":"ffffff23"},{"time":18.3667,"color":"ffffffc7"},{"time":20.0333,"color":"ffffff23"},{"time":21.6667,"color":"ffffffc7"},{"time":23.3333,"color":"ffffff23"},{"time":25.0333,"color":"ffffffc7"},{"time":26.7,"color":"ffffff23"},{"time":28.3333,"color":"ffffffc7"},{"time":30,"color":"ffffff23"},{"time":31.7,"color":"ffffffc7"},{"time":33.3667,"color":"ffffff23"},{"time":35,"color":"ffffffc7"},{"time":36.6667,"color":"ffffff23"}]},"Planet_02_line_glow3":{"rgba":[{"time":48.3,"color":"ffffff23"},{"time":49.9667,"color":"ffffffc7"},{"time":51.6333,"color":"ffffff23"},{"time":53.3,"color":"ffffffc7"},{"time":54.9667,"color":"ffffff23"},{"time":56.6333,"color":"ffffffc7"},{"time":58.3,"color":"ffffff23"},{"time":60,"color":"ffffffc7"},{"time":61.6667,"color":"ffffff23"},{"time":63.3,"color":"ffffffc7"},{"time":64.9667,"color":"ffffff23"},{"time":66.6667,"color":"ffffffc7"},{"time":68.3333,"color":"ffffff23"},{"time":69.9667,"color":"ffffffc7"},{"time":71.6333,"color":"ffffff23"},{"time":73.3333,"color":"ffffffc7"},{"time":75,"color":"ffffff23"},{"time":76.6333,"color":"ffffffc7"},{"time":78.3,"color":"ffffff23"},{"time":80,"color":"ffffffc7"},{"time":81.6667,"color":"ffffff23"},{"time":83.3333,"color":"ffffffc7"},{"time":85,"color":"ffffff23"},{"time":86.6667,"color":"ffffffc7"},{"time":88.3333,"color":"ffffff23"},{"time":90.0333,"color":"ffffffc7"},{"time":91.7,"color":"ffffff23"},{"time":93.3667,"color":"ffffffc7"},{"time":95.0333,"color":"ffffff23"},{"time":96.7,"color":"ffffffc7"},{"time":98.3667,"color":"ffffff23"}]},"Planet_09_line_glow":{"rgba":[{"color":"ffffff35"},{"time":3.3333,"color":"ffffff8c"},{"time":6.6667,"color":"ffffff35"},{"time":10,"color":"ffffff8c"},{"time":13.3333,"color":"ffffff35"},{"time":16.6667,"color":"ffffff8c"},{"time":20,"color":"ffffff35"},{"time":23.3333,"color":"ffffff8c"},{"time":26.7,"color":"ffffff35"},{"time":30.0333,"color":"ffffff8c"}],"attachment":[{"name":"Planet_09_line_glow"}]},"Planet_09_line_glow3":{"rgba":[{"time":69.9667,"color":"ffffff35"},{"time":73.3,"color":"ffffff8c"},{"time":76.6333,"color":"ffffff35"},{"time":79.9667,"color":"ffffff8c"},{"time":83.3,"color":"ffffff35"},{"time":86.6333,"color":"ffffff8c"},{"time":89.9667,"color":"ffffff35"},{"time":93.3,"color":"ffffff8c"},{"time":96.6667,"color":"ffffff35"}],"attachment":[{"name":"Planet_09_line_glow"}]}},"bones":{"Planet":{"rotate":[{"curve":[5.547,0,99.853,-140]},{"time":100,"value":-140}]},"Planet_05":{"rotate":[{"value":10},{"time":60,"value":131.73}]},"Planet_02":{"rotate":[{"value":-3},{"time":60,"value":100}]},"Planet_03":{"rotate":[{"value":12.15}],"translate":[{"x":-182.86,"y":169.12}]},"Planet_04":{"rotate":[{"value":5}]},"Planet_09":{"rotate":[{"value":24},{"time":60,"value":40}]},"Metoer":{"translate":[{"x":970.13,"y":1132.1},{"time":33.3333,"x":-3569.53,"y":-1754.32}]},"meteor_07":{"rotate":[{"value":0.03},{"time":26.5667,"value":-150}]},"meteor_06":{"rotate":[{},{"time":26.5667,"value":-116}]},"meteor_04":{"rotate":[{},{"time":26.5667,"value":162}]},"meteor_02":{"rotate":[{},{"time":26.5667,"value":-137.17}]},"meteor_01":{"rotate":[{},{"time":26.5667,"value":188.25}]},"meteor_03":{"rotate":[{},{"time":26.5667,"value":287.33}]},"meteor_05":{"rotate":[{},{"time":26.5667,"value":-90}]},"meteor_08":{"rotate":[{"value":0.03},{"time":26.5667,"value":141.77}]},"Asteroid_01":{"rotate":[{},{"time":26.7333,"value":-240.8}]},"Asteroid":{"translate":[{"x":961.06,"y":902.17},{"time":33.3333,"x":-3524.55,"y":-1836.86}]},"Planet_02_line_glow":{"scale":[{"x":0.929}],"shear":[{"x":8.55}]},"Planet_021":{"rotate":[{},{"time":60,"value":-120}],"translate":[{"x":-28.03,"y":22.3}]},"Planet_022":{"rotate":[{"value":10}]},"Planet_023":{"rotate":[{"value":5}]},"Planet_024":{"rotate":[{"value":12.15}],"translate":[{"x":-182.86,"y":169.12}]},"Planet_02_line_glow3":{"scale":[{"x":0.929}],"shear":[{"x":8.55}]},"Planet_025":{"rotate":[{"value":-3}]},"Planet_026":{"rotate":[{"value":24}]},"Planet3":{"rotate":[{"value":-120},{"time":100,"value":-240}]},"Planet_027":{"rotate":[{},{"time":60,"value":-50}],"translate":[{"x":-28.03,"y":22.3}]},"front":{"translate":[{},{"time":20,"x":87.46,"y":-113.52},{"time":40,"x":-14.02,"y":-35.04},{"time":70.0333,"x":87.46,"y":-113.52},{"time":100}]},"back":{"translate":[{"time":100,"x":-502.62,"y":-56.66}]},"meteor_09":{"rotate":[{"time":33.2667,"value":0.03},{"time":59.9,"value":133.45}]},"meteor_010":{"rotate":[{"time":33.2667,"value":0.03},{"time":59.9,"value":-150}]},"meteor_011":{"rotate":[{"time":33.2667},{"time":59.9,"value":198.23}]},"meteor_012":{"rotate":[{"time":33.2667},{"time":59.9,"value":-89.1}]},"meteor_013":{"rotate":[{"time":33.2667},{"time":59.9,"value":117.45}]},"meteor_014":{"rotate":[{"time":33.2667},{"time":59.9,"value":287.33}]},"meteor_015":{"rotate":[{"time":33.2667},{"time":59.9,"value":-137.03}]},"meteor_016":{"rotate":[{"time":33.2667},{"time":59.9,"value":156.6}]},"Metoer2":{"translate":[{"x":970.13,"y":1132.1,"curve":"stepped"},{"time":33.3333,"x":970.13,"y":1132.1},{"time":66.6667,"x":-3569.53,"y":-1754.32}]},"meteor_017":{"rotate":[{"time":69.0667,"value":0.03},{"time":95.7,"value":137.95}]},"meteor_018":{"rotate":[{"time":69.0667,"value":0.03},{"time":95.7,"value":-210.75}]},"meteor_019":{"rotate":[{"time":69.0667},{"time":95.7,"value":211.72}]},"meteor_020":{"rotate":[{"time":69.0667},{"time":95.7,"value":-122.62}]},"meteor_021":{"rotate":[{"time":69.0667},{"time":95.7,"value":178.43}]},"meteor_022":{"rotate":[{"time":69.0667},{"time":95.7,"value":298.58}]},"meteor_023":{"rotate":[{"time":69.0667},{"time":95.7,"value":-173.48}]},"meteor_024":{"rotate":[{"time":69.0667},{"time":95.7,"value":128.7}]},"Metoer3":{"translate":[{"x":970.13,"y":1132.1,"curve":"stepped"},{"time":66.6667,"x":970.13,"y":1132.1},{"time":100,"x":-3569.53,"y":-1754.32}]},"Asteroid_06":{"rotate":[{"time":36.2667},{"time":63,"value":-108.9}]},"Asteroid2":{"translate":[{"x":961.06,"y":902.17,"curve":"stepped"},{"time":33.3333,"x":961.06,"y":902.17},{"time":66.6667,"x":-3524.55,"y":-1836.86}]},"Asteroid_011":{"rotate":[{"time":71.0333},{"time":97.7667,"value":-65.93}]},"Asteroid3":{"translate":[{"x":961.06,"y":902.17,"curve":"stepped"},{"time":66.6667,"x":961.06,"y":902.17},{"time":100,"x":-3524.55,"y":-1836.86}]},"bg_light":{"translate":[{"y":6}],"scale":[{"x":1.332,"y":2.013}]},"Planet_02_line":{"scale":[{"x":0.929}],"shear":[{"x":8.55}]},"Planet_02_line3":{"scale":[{"x":0.929}],"shear":[{"x":8.55}]}}}}}